CHANGELOG.md
LICENSE
README.md
pycounts_k108/__init__.py
pycounts_k108/data/__init__.py
pycounts_k108/data/flatland.txt
pycounts_k108/datasets.py
pycounts_k108/plotting.py
pycounts_k108/pycounts.py
pycounts_k108-0.3.0.dist-info/METADATA
pycounts_k108-0.3.0.dist-info/LICENSE
pycounts_k108-0.3.0.dist-info/WHEEL
pycounts_k108-0.3.0.dist-info/RECORD
