Metadata-Version: 2.1
Name: pycounts-k108
Version: 0.3.0
Summary: Calculate word counts in a text file!
License: MIT
Author: Tony Kabilan Okeke
Requires-Python: >=3.10,<4.0
Classifier: License :: OSI Approved :: MIT License
Classifier: Programming Language :: Python :: 3
Classifier: Programming Language :: Python :: 3.10
Classifier: Programming Language :: Python :: 3.11
Requires-Dist: matplotlib (>=3.6.2,<4.0.0)
